alpacafarmer/__init__.py
alpacafarmer/auth.py
alpacafarmer/client.py
alpacafarmer/exceptions.py
alpacafarmer/http.py
alpacafarmer/models.py
alpacafarmer/py.typed
alpacafarmer-0.1.10.dist-info/METADATA
alpacafarmer-0.1.10.dist-info/WHEEL
alpacafarmer-0.1.10.dist-info/licenses/LICENSE
alpacafarmer-0.1.10.dist-info/RECORD
