Metadata-Version: 2.4
Name: alpacafarmer
Version: 0.1.10
Summary: A minimal Python wrapper for Alpaca Markets API
Project-URL: Homepage, https://github.com/alpacafarmer/alpacafarmer
Project-URL: Documentation, https://github.com/alpacafarmer/alpacafarmer#readme
Project-URL: Repository, https://github.com/alpacafarmer/alpacafarmer
Project-URL: Issues, https://github.com/alpacafarmer/alpacafarmer/issues
Author: AlpacaFarmer Team
License: MIT
License-File: LICENSE
Keywords: alpaca,api,crypto,finance,stocks,trading
Classifier: Development Status :: 3 - Alpha
Classifier: Intended Audience :: Developers
Classifier: Intended Audience :: Financial and Insurance Industry
Classifier: License :: OSI Approved :: MIT License
Classifier: Operating System :: OS Independent
Classifier: Programming Language :: Python :: 3
Classifier: Programming Language :: Python :: 3.10
Classifier: Programming Language :: Python :: 3.11
Classifier: Programming Language :: Python :: 3.12
Classifier: Topic :: Office/Business :: Financial :: Investment
Classifier: Typing :: Typed
Requires-Python: >=3.10
Requires-Dist: httpx>=0.27.0
Requires-Dist: pydantic>=2.5.0
Provides-Extra: dev
Requires-Dist: pytest-asyncio>=0.23.0; extra == 'dev'
Requires-Dist: pytest-httpx>=0.30.0; extra == 'dev'
Requires-Dist: pytest>=8.0.0; extra == 'dev'
Requires-Dist: python-dotenv>=1.0.0; extra == 'dev'
